lmspro/__init__.py
lmspro/course_manager.py
lmspro/data_manager.py
lmspro/enrollment_manager.py
lmspro/input_helper.py
lmspro/library_manager.py
lmspro/main.py
lmspro/report_manager.py
lmspro/student_manager.py
lmspro-1.0.3.dist-info/METADATA
lmspro-1.0.3.dist-info/WHEEL
lmspro-1.0.3.dist-info/top_level.txt
lmspro-1.0.3.dist-info/RECORD
