Metadata-Version: 2.4
Name: lmspro
Version: 1.0.3
Summary: Professional LMS: Students, Courses, Library, Enrollments, Reports
Home-page: https://github.com/yourusername/lmspro
Author: Your Name
Author-email: SHAFIQUL ISLAM <shafiqul.cmt@gmail.com>
License: MIT
Project-URL: Homepage, https://github.com/shafiqul8/lmspro
Keywords: LMS,Library Management,Course Management,Python CLI
Requires-Python: >=3.10
